varnishadm.py
python_varnishadm-0.2.2.data/scripts/varnish_manager
python_varnishadm-0.2.2.dist-info/DESCRIPTION.rst
python_varnishadm-0.2.2.dist-info/top_level.txt
python_varnishadm-0.2.2.dist-info/metadata.json
python_varnishadm-0.2.2.dist-info/WHEEL
python_varnishadm-0.2.2.dist-info/RECORD
python_varnishadm-0.2.2.dist-info/METADATA
