Metadata-Version: 2.0
Name: python-varnishadm
Version: 0.2.2
Summary: Simple Python interface for the Varnish management port
Home-page: http://github.com/ByteInternet/python-varnishadm
Author: Justin Quick
Author-email: justquick@gmail.com
License: UNKNOWN
Platform: UNKNOWN
Classifier: Development Status :: 5 - Production/Stable
Classifier: Environment :: Console
Classifier: Intended Audience :: Developers
Classifier: License :: OSI Approved :: BSD License
Classifier: Operating System :: OS Independent
Classifier: Programming Language :: Python
Classifier: Topic :: Utilities
